shellit/__init__.py
shellit/shellit.py
shellit-0.0.4.dist-info/LICENSE
shellit-0.0.4.dist-info/METADATA
shellit-0.0.4.dist-info/WHEEL
shellit-0.0.4.dist-info/top_level.txt
shellit-0.0.4.dist-info/RECORD
