Metadata-Version: 2.1
Name: shellit
Version: 0.0.4
Summary: Run shell commands with python and get returncode,outputs as python variables. Also it will simultaneously print the outputs
Home-page: https://github.com/amitdev101/shellit
Author: amit
License: UNKNOWN
Keywords: shellit,autoshell,shell,run shell in python,amitdev101,amit,amit-package-tutorial,tutorial
Platform: UNKNOWN
Classifier: Development Status :: 3 - Alpha
Classifier: Intended Audience :: Education
Classifier: Programming Language :: Python :: 2
Classifier: Programming Language :: Python :: 3
Classifier: Operating System :: MacOS :: MacOS X
Classifier: Operating System :: Microsoft :: Windows
